gradio/__init__.py
gradio/analytics.py
gradio/blocks.py
gradio/cli.py
gradio/context.py
gradio/data_classes.py
gradio/deploy_space.py
gradio/deprecation.py
gradio/events.py
gradio/exceptions.py
gradio/external.py
gradio/external_utils.py
gradio/flagging.py
gradio/helpers.py
gradio/inputs.py
gradio/interface.py
gradio/interpretation.py
gradio/ipython_ext.py
gradio/layouts.py
gradio/mix.py
gradio/networking.py
gradio/outputs.py
gradio/pipelines.py
gradio/processing_utils.py
gradio/queueing.py
gradio/ranged_response.py
gradio/reload.py
gradio/routes.py
gradio/strings.py
gradio/templates.py
gradio/tunneling.py
gradio/utils.py
gradio/components/__init__.py
gradio/components/annotated_image.py
gradio/components/audio.py
gradio/components/bar_plot.py
gradio/components/base.py
gradio/components/button.py
gradio/components/carousel.py
gradio/components/chatbot.py
gradio/components/checkbox.py
gradio/components/checkboxgroup.py
gradio/components/clear_button.py
gradio/components/code.py
gradio/components/color_picker.py
gradio/components/dataframe.py
gradio/components/dataset.py
gradio/components/dropdown.py
gradio/components/duplicate_button.py
gradio/components/file.py
gradio/components/gallery.py
gradio/components/highlighted_text.py
gradio/components/html.py
gradio/components/image.py
gradio/components/interpretation.py
gradio/components/json_component.py
gradio/components/label.py
gradio/components/line_plot.py
gradio/components/markdown.py
gradio/components/model3d.py
gradio/components/number.py
gradio/components/plot.py
gradio/components/radio.py
gradio/components/scatter_plot.py
gradio/components/slider.py
gradio/components/state.py
gradio/components/status_tracker.py
gradio/components/textbox.py
gradio/components/timeseries.py
gradio/components/upload_button.py
gradio/components/video.py
gradio/themes/__init__.py
gradio/themes/app.py
gradio/themes/base.py
gradio/themes/builder_app.py
gradio/themes/default.py
gradio/themes/glass.py
gradio/themes/monochrome.py
graudio-3.35.2.dist-info/METADATA
graudio-3.35.2.dist-info/WHEEL
graudio-3.35.2.dist-info/entry_points.txt
graudio-3.35.2.dist-info/licenses/LICENSE
graudio-3.35.2.dist-info/RECORD
